genomicsdb/__init__.py
genomicsdb/genomicsdb.cpython-312-darwin.so
genomicsdb/.dylibs/libtiledbgenomicsdb.1.5.4.dylib
genomicsdb/scripts/genomicsdb_common.py
genomicsdb/scripts/__init__.py
genomicsdb/scripts/README.md
genomicsdb/scripts/genomicsdb_cache.py
genomicsdb/scripts/genomicsdb_query.py
genomicsdb/protobuf/genomicsdb_vid_mapping_pb2.py
genomicsdb/protobuf/__init__.py
genomicsdb/protobuf/README.md
genomicsdb/protobuf/genomicsdb_import_config_pb2.py
genomicsdb/protobuf/genomicsdb_coordinates_pb2.py
genomicsdb/protobuf/.gitignore
genomicsdb/protobuf/genomicsdb_export_config_pb2.py
genomicsdb/protobuf/genomicsdb_callsets_mapping_pb2.py
genomicsdb-0.1.6.dist-info/RECORD
genomicsdb-0.1.6.dist-info/WHEEL
genomicsdb-0.1.6.dist-info/entry_points.txt
genomicsdb-0.1.6.dist-info/top_level.txt
genomicsdb-0.1.6.dist-info/METADATA
genomicsdb-0.1.6.dist-info/licenses/LICENSE
