Metadata-Version: 2.4
Name: genomicsdb
Version: 0.1.6
Summary: Python Bindings for querying GenomicsDB
Author: GenomicsDB.org
Author-email: support@genomicsdb.org
Maintainer: GenomicsDB.org
Maintainer-email: support@genomicsdb.org
License: MIT
Keywords: genomics,genomicsdb,variant,vcf,variant calls
Classifier: Development Status :: 5 - Production/Stable
Classifier: Intended Audience :: Developers
Classifier: Intended Audience :: Information Technology
Classifier: Intended Audience :: Science/Research
Classifier: License :: OSI Approved :: MIT License
Classifier: Topic :: Software Development :: Libraries :: Python Modules
Classifier: Operating System :: POSIX :: Linux
Classifier: Operating System :: MacOS :: MacOS X
Classifier: Programming Language :: Python :: 3.9
Classifier: Programming Language :: Python :: 3.10
Classifier: Programming Language :: Python :: 3.11
Classifier: Programming Language :: Python :: 3.12
Requires-Python: >=3.9
License-File: LICENSE
Requires-Dist: numpy<2.0.0,>=1.24.0
Requires-Dist: pandas>=2.1.0
Requires-Dist: protobuf>=4.21.1
Requires-Dist: pyarrow>=14.0.0
Dynamic: author
Dynamic: author-email
Dynamic: classifier
Dynamic: description
Dynamic: description-content-type
Dynamic: keywords
Dynamic: license
Dynamic: license-file
Dynamic: maintainer
Dynamic: maintainer-email
Dynamic: requires-dist
Dynamic: requires-python
Dynamic: summary
